qdb_cloudwatch/__main__.py
qdb_cloudwatch/check.py
qdb_cloudwatch/cloudwatch.py
qdb_cloudwatch/driver.py
qdb_cloudwatch-3.14.2.dist-info/licenses/LICENSE.md
qdb_cloudwatch-3.14.2.dist-info/METADATA
qdb_cloudwatch-3.14.2.dist-info/WHEEL
qdb_cloudwatch-3.14.2.dist-info/entry_points.txt
qdb_cloudwatch-3.14.2.dist-info/top_level.txt
qdb_cloudwatch-3.14.2.dist-info/RECORD
