Metadata-Version: 2.4
Name: qdb-cloudwatch
Version: 3.14.2
Summary: Export QuasarDB statistics to AWS Cloudwatch
License-File: LICENSE.md
Requires-Dist: boto3>=1.9
Requires-Dist: quasardb==3.14.2
Provides-Extra: pandas
Requires-Dist: pandas; extra == "pandas"
Provides-Extra: tests
Requires-Dist: pytest>=6.2.5; extra == "tests"
Requires-Dist: pytest-runner>=5.3.1; extra == "tests"
Requires-Dist: teamcity-messages>=1.29; extra == "tests"
Dynamic: license-file
Dynamic: provides-extra
Dynamic: requires-dist
Dynamic: summary
